{
  "epochs": 32,
  "batch_size": 64,
  "validation_split": 0.15,
  "early_stopping_patience": 8,
  "base_lr": 0.0006,
  "optimizer": "adam",
  "weight_decay": 0.00012,
  "adam_beta1": 0.9,
  "adam_beta2": 0.999,
  "adam_epsilon": 1e-8,
  "scheduler": "cosine",
  "step_size": 6,
  "gamma": 0.94,
  "min_lr": 0.00001,
  "label_smoothing": 0.02,
  "use_class_weights": true,
  "class_weights_path": "../data/class_weights.txt",
  "use_actor_critic": true,
  "policy_loss_weight": 1.0,
  "value_loss_weight": 0.5,
  "reward_scale": 1.0,
  "entropy_coeff": 0.012
}
